README.md
setup.py
pulumiverse_mssql/__init__.py
pulumiverse_mssql/_inputs.py
pulumiverse_mssql/_utilities.py
pulumiverse_mssql/azuread_service_principal.py
pulumiverse_mssql/azuread_user.py
pulumiverse_mssql/database.py
pulumiverse_mssql/database_permission.py
pulumiverse_mssql/database_role.py
pulumiverse_mssql/database_role_member.py
pulumiverse_mssql/get_azuread_service_principal.py
pulumiverse_mssql/get_azuread_user.py
pulumiverse_mssql/get_database.py
pulumiverse_mssql/get_database_permissions.py
pulumiverse_mssql/get_database_role.py
pulumiverse_mssql/get_database_roles.py
pulumiverse_mssql/get_databases.py
pulumiverse_mssql/get_query.py
pulumiverse_mssql/get_schema.py
pulumiverse_mssql/get_schema_permissions.py
pulumiverse_mssql/get_schemas.py
pulumiverse_mssql/get_server_permissions.py
pulumiverse_mssql/get_server_role.py
pulumiverse_mssql/get_server_roles.py
pulumiverse_mssql/get_sql_login.py
pulumiverse_mssql/get_sql_logins.py
pulumiverse_mssql/get_sql_user.py
pulumiverse_mssql/get_sql_users.py
pulumiverse_mssql/outputs.py
pulumiverse_mssql/provider.py
pulumiverse_mssql/pulumi-plugin.json
pulumiverse_mssql/py.typed
pulumiverse_mssql/schema.py
pulumiverse_mssql/schema_permission.py
pulumiverse_mssql/script.py
pulumiverse_mssql/server_permission.py
pulumiverse_mssql/server_role.py
pulumiverse_mssql/server_role_member.py
pulumiverse_mssql/sql_login.py
pulumiverse_mssql/sql_user.py
pulumiverse_mssql.egg-info/PKG-INFO
pulumiverse_mssql.egg-info/SOURCES.txt
pulumiverse_mssql.egg-info/dependency_links.txt
pulumiverse_mssql.egg-info/not-zip-safe
pulumiverse_mssql.egg-info/requires.txt
pulumiverse_mssql.egg-info/top_level.txt
pulumiverse_mssql/config/__init__.py
pulumiverse_mssql/config/outputs.py
pulumiverse_mssql/config/vars.py