Metadata-Version: 2.1
Name: pulumiverse-mssql
Version: 0.0.7
Summary: A Pulumi Provider for Microsoft SQL Server and Azure SQL
Home-page: https://github.com/pulumiverse/pulumi-mssql
License: Apache-2.0
Project-URL: Repository, https://github.com/pulumiverse/pulumi-mssql
Keywords: pulumi mssql category/database
Platform: UNKNOWN
Requires-Python: >=3.7
